ignos/__init__.py
ignos/internal/__init__.py
ignos/internal/api/__init__.py
ignos/internal/api/client/__init__.py
ignos/internal/api/client/_client.py
ignos/internal/api/client/_configuration.py
ignos/internal/api/client/_patch.py
ignos/internal/api/client/_version.py
ignos/internal/api/client/py.typed
ignos/internal/api/client/_utils/__init__.py
ignos/internal/api/client/_utils/serialization.py
ignos/internal/api/client/aio/__init__.py
ignos/internal/api/client/aio/_client.py
ignos/internal/api/client/aio/_configuration.py
ignos/internal/api/client/aio/_patch.py
ignos/internal/api/client/aio/operations/__init__.py
ignos/internal/api/client/aio/operations/_operations.py
ignos/internal/api/client/aio/operations/_patch.py
ignos/internal/api/client/models/__init__.py
ignos/internal/api/client/models/_enums.py
ignos/internal/api/client/models/_models.py
ignos/internal/api/client/models/_patch.py
ignos/internal/api/client/operations/__init__.py
ignos/internal/api/client/operations/_operations.py
ignos/internal/api/client/operations/_patch.py
ignos_internal_api_client-20250905.0.12525.dist-info/METADATA
ignos_internal_api_client-20250905.0.12525.dist-info/WHEEL
ignos_internal_api_client-20250905.0.12525.dist-info/top_level.txt
ignos_internal_api_client-20250905.0.12525.dist-info/RECORD
