Metadata-Version: 2.4
Name: ignos-internal-api-client
Version: 20250905.0.12525
Summary: ignos-internal-api-client
Home-page: 
Author-email: 
Keywords: azure,azure sdk
Requires-Dist: isodate>=0.6.1
Requires-Dist: azure-core>=1.35.0
Requires-Dist: typing-extensions>=4.6.0
Dynamic: description
Dynamic: keywords
Dynamic: requires-dist
Dynamic: summary
